lefshift/__init__.py
lefshift/__main__.py
lefshift/application_utils.py
lefshift/constants.py
lefshift/fp.py
lefshift/model.py
lefshift/predict.py
lefshift/split.py
lefshift/train.py
lefshift/utils.py
lefshift-0.5.3.dist-info/LICENSE.md
lefshift-0.5.3.dist-info/METADATA
lefshift-0.5.3.dist-info/WHEEL
lefshift-0.5.3.dist-info/entry_points.txt
lefshift-0.5.3.dist-info/top_level.txt
lefshift-0.5.3.dist-info/RECORD
