Metadata-Version: 2.1
Name: lefshift
Version: 0.5.3
Summary: Predict 19F chemical shift
Author-email: Patrick Penner <patrick@ppenner.com>
Project-URL: Homepage, https://github.com/PatrickPenner/lefshift
Project-URL: Issues, https://github.com/PatrickPenner/lefshift/issues
Classifier: Programming Language :: Python :: 3
Classifier: License :: OSI Approved :: MIT License
Classifier: License :: OSI Approved :: Apache Software License
Classifier: Operating System :: OS Independent
Requires-Python: >=3.8
License-File: LICENSE.md
Requires-Dist: numpy >=1.23.5
Requires-Dist: pandas >=1.5.2
Requires-Dist: rdkit >=2022.09.3
Requires-Dist: scikit-learn >=1.2.0
Requires-Dist: xgboost >=1.7.1
